database/__init__.py
database/db_creation.py
edges/__init__.py
edges/edge_manipulation.py
email_data/__init__.py
email_data/email.py
email_data/utils/__init__.py
email_data/utils/email_database_manipulation.py
email_data/utils/email_tree.py
email_data/utils/validator.py
graphce/__init__.py
graphce/tree.py
ip_profile/__init__.py
ip_profile/exceptions.py
ip_profile/ip.py
ip_profile/ip_object.py
ip_profile/ipv4.py
ip_profile/ipv6.py
ip_profile/utils/__init__.py
ip_profile/utils/common.py
ip_profile/utils/ip_data_manipulation.py
ip_profile/utils/ip_tree.py
ip_profile/utils/validator.py
phone_data/__init__.py
phone_data/exceptions.py
phone_data/phone.py
phone_data/utils/__init__.py
phone_data/utils/phone_database_manipulation.py
phone_data/utils/phone_tree.py
phone_data/utils/validator.py
graphce-0.0.2.dist-info/METADATA
graphce-0.0.2.dist-info/WHEEL
graphce-0.0.2.dist-info/top_level.txt
graphce-0.0.2.dist-info/RECORD
