Metadata-Version: 2.1
Name: graphce
Version: 0.0.2
Summary: Working with databases related to IP, phone, and email information.
Author: authsafe
Requires-Dist: sqlitedict
Requires-Dist: phonenumbers
